joes_ntpdate/__init__.py
joes_ntpdate/joes_ntpdate.py
joes_ntpdate/retryable.py
joes_ntpdate-1.9.78.dist-info/DESCRIPTION.rst
joes_ntpdate-1.9.78.dist-info/entry_points.txt
joes_ntpdate-1.9.78.dist-info/METADATA
joes_ntpdate-1.9.78.dist-info/metadata.json
joes_ntpdate-1.9.78.dist-info/RECORD
joes_ntpdate-1.9.78.dist-info/top_level.txt
joes_ntpdate-1.9.78.dist-info/WHEEL
joes_ntpdate-1.9.78.dist-info/zip-safe
