Metadata-Version: 2.0
Name: joes-ntpdate
Version: 1.9.78
Summary: Joe's own ntpdate: set the date and time via NTP
Home-page: https://github.com/jquast/joes-ntpdate
Author: Jeff Quast
Author-email: contact@jeffquast.com
License: MIT
Keywords: ntpdate,hwclock,time,clock,synchronize
Platform: UNKNOWN
Classifier: Topic :: System :: Networking :: Time Synchronization
Classifier: Natural Language :: English
Classifier: Development Status :: 5 - Production/Stable
Classifier: Environment :: Console
Classifier: Environment :: Console :: Curses
Classifier: License :: OSI Approved :: MIT License
Classifier: Operating System :: POSIX
Classifier: Operating System :: MacOS :: MacOS X
Classifier: Operating System :: POSIX :: BSD :: OpenBSD
Classifier: Operating System :: POSIX :: Linux
Classifier: Programming Language :: Python :: 2
Classifier: Programming Language :: Python :: 2.7
Classifier: Programming Language :: Python :: 3
Classifier: Programming Language :: Python :: 3.2
Classifier: Programming Language :: Python :: 3.3
Classifier: Programming Language :: Python :: 3.4
Classifier: Topic :: Software Development :: User Interfaces
Requires-Dist: ntplib (>=0.3.2)
